itlubber_automl/__init__.py
itlubber_automl/model.py
itlubber_automl/utils/__init__.py
itlubber_automl/utils/logger.py
itlubber_automl/utils/methods.py
itlubber_automl/utils/metrics.py
itlubber_automl-0.1.3.dist-info/METADATA
itlubber_automl-0.1.3.dist-info/WHEEL
itlubber_automl-0.1.3.dist-info/top_level.txt
itlubber_automl-0.1.3.dist-info/RECORD
